takeonme/__init__.py
takeonme/aws/__init__.py
takeonme/aws/commands.py
takeonme/aws/ec2.py
takeonme/aws/route53.py
takeonme/cli.py
takeonme/gcp/__init__.py
takeonme/gcp/cloud_dns.py
takeonme/gcp/commands.py
takeonme/util.py
takeonme-0.4.0.dist-info/entry_points.txt
takeonme-0.4.0.dist-info/LICENSE
takeonme-0.4.0.dist-info/WHEEL
takeonme-0.4.0.dist-info/METADATA
takeonme-0.4.0.dist-info/RECORD
